programgarden_core/__init__.py
programgarden_core/alias_resolver.py
programgarden_core/bases/__init__.py
programgarden_core/bases/base.py
programgarden_core/bases/cancel_orders.py
programgarden_core/bases/client.py
programgarden_core/bases/components.py
programgarden_core/bases/mixins.py
programgarden_core/bases/modify_orders.py
programgarden_core/bases/new_orders.py
programgarden_core/bases/products.py
programgarden_core/bases/strategy.py
programgarden_core/bases/system.py
programgarden_core/exceptions.py
programgarden_core/korea_alias.py
programgarden_core/logs.py
programgarden_core-0.1.12.dist-info/METADATA
programgarden_core-0.1.12.dist-info/WHEEL
programgarden_core-0.1.12.dist-info/RECORD
