Metadata-Version: 2.3
Name: programgarden-core
Version: 0.1.12
Summary: 자동화매매 클래스 상속, 로그, 환경 등의 핵심이되는 오픈소스
Author: 프로그램동산
Author-email: coding@programgarden.com
Requires-Python: >=3.10
Classifier: Programming Language :: Python :: 3
Classifier: Programming Language :: Python :: 3.10
Classifier: Programming Language :: Python :: 3.11
Classifier: Programming Language :: Python :: 3.12
Classifier: Programming Language :: Python :: 3.13
Requires-Dist: typing-extensions (>=4.15.0,<5.0.0)
